pacc/__init__.py
pacc/__main__.py
pacc/cli.py
pacc/py.typed
pacc/core/__init__.py
pacc/core/config_demo.py
pacc/core/config_manager.py
pacc/core/file_utils.py
pacc/core/project_config.py
pacc/core/url_downloader.py
pacc/errors/__init__.py
pacc/errors/exceptions.py
pacc/errors/reporting.py
pacc/fragments/__init__.py
pacc/fragments/claude_md_manager.py
pacc/fragments/collection_manager.py
pacc/fragments/installation_manager.py
pacc/fragments/repository_manager.py
pacc/fragments/storage_manager.py
pacc/fragments/sync_manager.py
pacc/fragments/team_manager.py
pacc/fragments/update_manager.py
pacc/fragments/version_tracker.py
pacc/packaging/__init__.py
pacc/packaging/converters.py
pacc/packaging/formats.py
pacc/packaging/handlers.py
pacc/packaging/metadata.py
pacc/performance/__init__.py
pacc/performance/background_workers.py
pacc/performance/caching.py
pacc/performance/lazy_loading.py
pacc/performance/optimization.py
pacc/plugins/__init__.py
pacc/plugins/config.py
pacc/plugins/converter.py
pacc/plugins/creator.py
pacc/plugins/discovery.py
pacc/plugins/discovery_old.py
pacc/plugins/environment.py
pacc/plugins/marketplace.py
pacc/plugins/repository.py
pacc/plugins/sandbox.py
pacc/plugins/search.py
pacc/plugins/security.py
pacc/plugins/security_integration.py
pacc/recovery/__init__.py
pacc/recovery/diagnostics.py
pacc/recovery/retry.py
pacc/recovery/strategies.py
pacc/recovery/suggestions.py
pacc/security/__init__.py
pacc/security/security_measures.py
pacc/selection/__init__.py
pacc/selection/filters.py
pacc/selection/persistence.py
pacc/selection/types.py
pacc/selection/ui.py
pacc/selection/workflow.py
pacc/sources/__init__.py
pacc/sources/base.py
pacc/sources/git.py
pacc/sources/url.py
pacc/ui/__init__.py
pacc/ui/components.py
pacc/validation/__init__.py
pacc/validation/base.py
pacc/validation/formats.py
pacc/validators/__init__.py
pacc/validators/agents.py
pacc/validators/base.py
pacc/validators/commands.py
pacc/validators/demo.py
pacc/validators/fragment_validator.py
pacc_cli-1.1.2.dist-info/licenses/LICENSE
pacc_cli-1.1.2.dist-info/METADATA
pacc_cli-1.1.2.dist-info/WHEEL
pacc_cli-1.1.2.dist-info/entry_points.txt
pacc_cli-1.1.2.dist-info/top_level.txt
pacc_cli-1.1.2.dist-info/RECORD
