Metadata-Version: 2.4
Name: pacc-cli
Version: 1.1.2
Summary: Package manager for Claude Code - simplify installation and management of Claude Code extensions
Author-email: PACC Development Team <pacc@example.com>
Maintainer-email: PACC Development Team <pacc@example.com>
License: MIT
Project-URL: Homepage, https://github.com/anthropics/pacc
Project-URL: Repository, https://github.com/anthropics/pacc
Project-URL: Documentation, https://pacc.readthedocs.io
Project-URL: Bug Tracker, https://github.com/anthropics/pacc/issues
Project-URL: Changelog, https://github.com/anthropics/pacc/blob/main/CHANGELOG.md
Keywords: claude,claude-code,package-manager,extensions,hooks,mcp,agents,commands,cli,developer-tools
Classifier: Development Status :: 4 - Beta
Classifier: Intended Audience :: Developers
Classifier: Topic :: Software Development :: Libraries :: Python Modules
Classifier: Topic :: Software Development :: Build Tools
Classifier: Topic :: System :: Software Distribution
Classifier: Topic :: Utilities
Classifier: License :: OSI Approved :: MIT License
Classifier: Programming Language :: Python :: 3
Classifier: Programming Language :: Python :: 3.8
Classifier: Programming Language :: Python :: 3.9
Classifier: Programming Language :: Python :: 3.10
Classifier: Programming Language :: Python :: 3.11
Classifier: Programming Language :: Python :: 3.12
Classifier: Operating System :: OS Independent
Classifier: Environment :: Console
Classifier: Typing :: Typed
Requires-Python: >=3.8
License-File: LICENSE
Requires-Dist: PyYAML>=6.0
Requires-Dist: chardet>=5.2.0
Requires-Dist: psutil>=5.9.0
Provides-Extra: url
Requires-Dist: aiohttp>=3.8.0; extra == "url"
Requires-Dist: aiofiles>=0.8.0; extra == "url"
Provides-Extra: dev
Requires-Dist: pytest>=7.0.0; extra == "dev"
Requires-Dist: pytest-cov>=4.0.0; extra == "dev"
Requires-Dist: pytest-asyncio>=0.21.0; extra == "dev"
Requires-Dist: mypy>=1.0.0; extra == "dev"
Requires-Dist: ruff>=0.1.0; extra == "dev"
Requires-Dist: pre-commit>=3.0.0; extra == "dev"
Requires-Dist: bandit[toml]>=1.7.5; extra == "dev"
Requires-Dist: build>=1.0.0; extra == "dev"
Requires-Dist: twine>=4.0.0; extra == "dev"
Requires-Dist: tomli>=2.0.0; python_version < "3.11" and extra == "dev"
Provides-Extra: test
Requires-Dist: pytest>=7.0.0; extra == "test"
Requires-Dist: pytest-cov>=4.0.0; extra == "test"
Requires-Dist: pytest-asyncio>=0.21.0; extra == "test"
Requires-Dist: tomli>=2.0.0; python_version < "3.11" and extra == "test"
Provides-Extra: docs
Requires-Dist: mkdocs>=1.5.0; extra == "docs"
Requires-Dist: mkdocs-material>=9.0.0; extra == "docs"
Requires-Dist: mkdocstrings[python]>=0.24.0; extra == "docs"
Dynamic: license-file
